gridappsd_certs/__init__.py
gridappsd_certs/device_certs.py
gridappsd_certificate_store-0.2.2.dist-info/METADATA
gridappsd_certificate_store-0.2.2.dist-info/WHEEL
gridappsd_certificate_store-0.2.2.dist-info/RECORD
