Metadata-Version: 2.3
Name: gridappsd-certificate-store
Version: 0.2.2
Summary: Certificate generator for GridAppSD and IEEE 2030.5 devices
License: BSD-3-Clause
Author: C. Allwardt
Author-email: 3979063+craig8@users.noreply.github.com
Requires-Python: >=3.10,<4.0
Classifier: License :: OSI Approved :: BSD License
Classifier: Programming Language :: Python :: 3
Classifier: Programming Language :: Python :: 3.10
Classifier: Programming Language :: Python :: 3.11
Classifier: Programming Language :: Python :: 3.12
Classifier: Programming Language :: Python :: 3.13
Requires-Dist: cryptography (>=41.0.0,<42.0.0)
Requires-Dist: ipaddress (>=1.0.23,<2.0.0)
